fast_color_checker/LICENSE
fast_color_checker/README.MD
fast_color_checker/__init__.py
fast_color_checker/requirements.txt
fast_color_checker/thirdparty.json
fast_color_checker-0.10.dist-info/LICENSE.rst
fast_color_checker-0.10.dist-info/METADATA
fast_color_checker-0.10.dist-info/WHEEL
fast_color_checker-0.10.dist-info/top_level.txt
fast_color_checker-0.10.dist-info/RECORD
