Metadata-Version: 2.1
Name: fast-color-checker
Version: 0.10
Summary: A couple of fast algorithms for counting and locating colors in pictures
Home-page: https://github.com/hansalemaos/fast_color_checker
Author: Johannes Fischer
Author-email: <aulasparticularesdealemaosp@gmail.com>
License: MIT
Keywords: screenshot,adb,windows,hwnd,handle,bot,cv2
Classifier: Development Status :: 4 - Beta
Classifier: Programming Language :: Python :: 3 :: Only
Classifier: Programming Language :: Python :: 3.9
Classifier: Topic :: Scientific/Engineering :: Visualization
Classifier: Topic :: Software Development :: Libraries :: Python Modules
Classifier: Topic :: Text Editors :: Text Processing
Classifier: Topic :: Text Processing :: General
Classifier: Topic :: Text Processing :: Indexing
Classifier: Topic :: Text Processing :: Filters
Classifier: Topic :: Utilities
License-File: LICENSE.rst
Requires-Dist: a-cv2-imshow-thread
Requires-Dist: numpy
Requires-Dist: opencv-python
Requires-Dist: requests
